{
	"type": "FeatureCollection",
	"features": [{
		"type": "Feature",
		"properties": {
			"stroke": "#555555",
			"stroke-width": 2,
			"stroke-opacity": 1,
			"fill": "#B536F0",
			"fill-opacity": 0.5,
			"name": "Brick UNO"
		},
		"geometry": {
			"type": "Polygon",
			"coordinates": [
				[
	                [
	                  -103.373253,
	                  20.696018
	                ],
	                [
	                  -103.373313,
	                  20.696456
	                ],
	                [
	                  -103.373508,
	                  20.69683
	                ],
	                [
	                  -103.374333,
	                  20.698413
	                ],
	                [
	                  -103.374618,
	                  20.699012
	                ],
	                [
	                  -103.37486,
	                  20.699521
	                ],
	                [
	                  -103.374941,
	                  20.699749
	                ],
	                [
	                  -103.37533,
	                  20.700846
	                ],
	                [
	                  -103.375665,
	                  20.701788
	                ],
	                [
	                  -103.375755,
	                  20.702042
	                ],
	                [
	                  -103.376034,
	                  20.70285
	                ],
	                [
	                  -103.376248,
	                  20.70347
	                ],
	                [
	                  -103.37638,
	                  20.703853
	                ],
	                [
	                  -103.376483,
	                  20.704179
	                ],
	                [
	                  -103.376679,
	                  20.704795
	                ],
	                [
	                  -103.376824,
	                  20.705251
	                ],
	                [
	                  -103.37687,
	                  20.705514
	                ],
	                [
	                  -103.377873,
	                  20.705299
	                ],
	                [
	                  -103.378317,
	                  20.705133
	                ],
	                [
	                  -103.378864,
	                  20.70493
	                ],
	                [
	                  -103.37913,
	                  20.70483
	                ],
	                [
	                  -103.379313,
	                  20.704722
	                ],
	                [
	                  -103.380655,
	                  20.703934
	                ],
	                [
	                  -103.380779,
	                  20.703861
	                ],
	                [
	                  -103.381888,
	                  20.703247
	                ],
	                [
	                  -103.382249,
	                  20.703047
	                ],
	                [
	                  -103.382554,
	                  20.702878
	                ],
	                [
	                  -103.382655,
	                  20.702822
	                ],
	                [
	                  -103.383897,
	                  20.702162
	                ],
	                [
	                  -103.384284,
	                  20.701956
	                ],
	                [
	                  -103.384663,
	                  20.701755
	                ],
	                [
	                  -103.384996,
	                  20.701589
	                ],
	                [
	                  -103.385186,
	                  20.701468
	                ],
	                [
	                  -103.385863,
	                  20.70109
	                ],
	                [
	                  -103.385997,
	                  20.700986
	                ],
	                [
	                  -103.386536,
	                  20.70057
	                ],
	                [
	                  -103.386657,
	                  20.700476
	                ],
	                [
	                  -103.387004,
	                  20.700102
	                ],
	                [
	                  -103.387578,
	                  20.699483
	                ],
	                [
	                  -103.388203,
	                  20.698579
	                ],
	                [
	                  -103.388487,
	                  20.69817
	                ],
	                [
	                  -103.388922,
	                  20.697352
	                ],
	                [
	                  -103.389638,
	                  20.69719
	                ],
	                [
	                  -103.390535,
	                  20.696986
	                ],
	                [
	                  -103.390695,
	                  20.69695
	                ],
	                [
	                  -103.391107,
	                  20.696847
	                ],
	                [
	                  -103.39143,
	                  20.696766
	                ],
	                [
	                  -103.391728,
	                  20.696691
	                ],
	                [
	                  -103.391969,
	                  20.696631
	                ],
	                [
	                  -103.392192,
	                  20.696575
	                ],
	                [
	                  -103.392389,
	                  20.696526
	                ],
	                [
	                  -103.393104,
	                  20.696352
	                ],
	                [
	                  -103.392891,
	                  20.695597
	                ],
	                [
	                  -103.392688,
	                  20.694909
	                ],
	                [
	                  -103.39266,
	                  20.694917
	                ],
	                [
	                  -103.392466,
	                  20.694296
	                ],
	                [
	                  -103.392288,
	                  20.693726
	                ],
	                [
	                  -103.392122,
	                  20.693196
	                ],
	                [
	                  -103.391978,
	                  20.692737
	                ],
	                [
	                  -103.391818,
	                  20.692224
	                ],
	                [
	                  -103.391782,
	                  20.692113
	                ],
	                [
	                  -103.390216,
	                  20.692048
	                ],
	                [
	                  -103.389737,
	                  20.692028
	                ],
	                [
	                  -103.3885,
	                  20.691833
	                ],
	                [
	                  -103.386709,
	                  20.691551
	                ],
	                [
	                  -103.386366,
	                  20.691497
	                ],
	                [
	                  -103.384732,
	                  20.691222
	                ],
	                [
	                  -103.382787,
	                  20.690894
	                ],
	                [
	                  -103.382388,
	                  20.690827
	                ],
	                [
	                  -103.380856,
	                  20.690581
	                ],
	                [
	                  -103.380262,
	                  20.690486
	                ],
	                [
	                  -103.378845,
	                  20.690259
	                ],
	                [
	                  -103.378495,
	                  20.690217
	                ],
	                [
	                  -103.377197,
	                  20.690061
	                ],
	                [
	                  -103.377076,
	                  20.689977
	                ],
	                [
	                  -103.376778,
	                  20.690431
	                ],
	                [
	                  -103.376323,
	                  20.691121
	                ],
	                [
	                  -103.376069,
	                  20.691508
	                ],
	                [
	                  -103.375715,
	                  20.692045
	                ],
	                [
	                  -103.375337,
	                  20.692619
	                ],
	                [
	                  -103.375165,
	                  20.692881
	                ],
	                [
	                  -103.375092,
	                  20.692989
	                ],
	                [
	                  -103.374166,
	                  20.694364
	                ],
	                [
	                  -103.373523,
	                  20.695318
	                ],
	                [
	                  -103.373276,
	                  20.695668
	                ],
	                [
	                  -103.373295,
	                  20.695677
	                ],
	                [
	                  -103.373304,
	                  20.695682
	                ],
	                [
	                  -103.373312,
	                  20.695688
	                ],
	                [
	                  -103.373321,
	                  20.695694
	                ],
	                [
	                  -103.373328,
	                  20.6957
	                ],
	                [
	                  -103.373343,
	                  20.695714
	                ],
	                [
	                  -103.37335,
	                  20.695722
	                ],
	                [
	                  -103.373356,
	                  20.69573
	                ],
	                [
	                  -103.373362,
	                  20.695738
	                ],
	                [
	                  -103.373367,
	                  20.695746
	                ],
	                [
	                  -103.373372,
	                  20.695755
	                ],
	                [
	                  -103.373377,
	                  20.695764
	                ],
	                [
	                  -103.37338,
	                  20.695773
	                ],
	                [
	                  -103.373384,
	                  20.695782
	                ],
	                [
	                  -103.373387,
	                  20.695792
	                ],
	                [
	                  -103.373389,
	                  20.695801
	                ],
	                [
	                  -103.373391,
	                  20.695811
	                ],
	                [
	                  -103.373392,
	                  20.695821
	                ],
	                [
	                  -103.373393,
	                  20.695831
	                ],
	                [
	                  -103.373393,
	                  20.695841
	                ],
	                [
	                  -103.373393,
	                  20.69585
	                ],
	                [
	                  -103.373392,
	                  20.69586
	                ],
	                [
	                  -103.37339,
	                  20.69587
	                ],
	                [
	                  -103.373388,
	                  20.69588
	                ],
	                [
	                  -103.373386,
	                  20.695889
	                ],
	                [
	                  -103.373383,
	                  20.695898
	                ],
	                [
	                  -103.373379,
	                  20.695908
	                ],
	                [
	                  -103.373375,
	                  20.695917
	                ],
	                [
	                  -103.37337,
	                  20.695926
	                ],
	                [
	                  -103.373365,
	                  20.695934
	                ],
	                [
	                  -103.37336,
	                  20.695942
	                ],
	                [
	                  -103.373354,
	                  20.695951
	                ],
	                [
	                  -103.373347,
	                  20.695958
	                ],
	                [
	                  -103.37334,
	                  20.695966
	                ],
	                [
	                  -103.373325,
	                  20.695979
	                ],
	                [
	                  -103.373317,
	                  20.695986
	                ],
	                [
	                  -103.373309,
	                  20.695992
	                ],
	                [
	                  -103.3733,
	                  20.695997
	                ],
	                [
	                  -103.373291,
	                  20.696002
	                ],
	                [
	                  -103.373282,
	                  20.696007
	                ],
	                [
	                  -103.373273,
	                  20.696011
	                ],
	                [
	                  -103.373263,
	                  20.696015
	                ],
	                [
	                  -103.373253,
	                  20.696018
	                ]
				]
			]
		}
	}, {
		"type": "Feature",
		"properties": {
			"stroke": "#555555",
			"stroke-width": 2,
			"stroke-opacity": 1,
			"fill": "#F4A201",
			"fill-opacity": 0.5,
			"name": "Brick DOS"
		},
		"geometry": {
			"type": "Polygon",
			"coordinates": [
				[
	                [
	                  -103.383627,
	                  20.679463
	                ],
	                [
	                  -103.383708,
	                  20.679465
	                ],
	                [
	                  -103.384338,
	                  20.67948
	                ],
	                [
	                  -103.384421,
	                  20.679482
	                ],
	                [
	                  -103.385009,
	                  20.679501
	                ],
	                [
	                  -103.385739,
	                  20.679525
	                ],
	                [
	                  -103.386496,
	                  20.679551
	                ],
	                [
	                  -103.387006,
	                  20.67954
	                ],
	                [
	                  -103.387268,
	                  20.679577
	                ],
	                [
	                  -103.387998,
	                  20.679602
	                ],
	                [
	                  -103.388355,
	                  20.679614
	                ],
	                [
	                  -103.388852,
	                  20.679581
	                ],
	                [
	                  -103.389557,
	                  20.679534
	                ],
	                [
	                  -103.390303,
	                  20.679498
	                ],
	                [
	                  -103.390997,
	                  20.679463
	                ],
	                [
	                  -103.391588,
	                  20.679434
	                ],
	                [
	                  -103.391867,
	                  20.67942
	                ],
	                [
	                  -103.392031,
	                  20.6794
	                ],
	                [
	                  -103.393154,
	                  20.67926
	                ],
	                [
	                  -103.39316,
	                  20.679277
	                ],
	                [
	                  -103.393167,
	                  20.679293
	                ],
	                [
	                  -103.393175,
	                  20.679309
	                ],
	                [
	                  -103.393184,
	                  20.679325
	                ],
	                [
	                  -103.393194,
	                  20.679341
	                ],
	                [
	                  -103.393205,
	                  20.679355
	                ],
	                [
	                  -103.393216,
	                  20.67937
	                ],
	                [
	                  -103.393228,
	                  20.679383
	                ],
	                [
	                  -103.393241,
	                  20.679397
	                ],
	                [
	                  -103.393255,
	                  20.679409
	                ],
	                [
	                  -103.393269,
	                  20.679421
	                ],
	                [
	                  -103.393284,
	                  20.679432
	                ],
	                [
	                  -103.3933,
	                  20.679442
	                ],
	                [
	                  -103.393316,
	                  20.679452
	                ],
	                [
	                  -103.393333,
	                  20.67946
	                ],
	                [
	                  -103.39335,
	                  20.679468
	                ],
	                [
	                  -103.393367,
	                  20.679475
	                ],
	                [
	                  -103.393385,
	                  20.679481
	                ],
	                [
	                  -103.393403,
	                  20.679487
	                ],
	                [
	                  -103.393422,
	                  20.679491
	                ],
	                [
	                  -103.39344,
	                  20.679494
	                ],
	                [
	                  -103.393459,
	                  20.679497
	                ],
	                [
	                  -103.393478,
	                  20.679498
	                ],
	                [
	                  -103.393497,
	                  20.679499
	                ],
	                [
	                  -103.393516,
	                  20.679499
	                ],
	                [
	                  -103.393535,
	                  20.679498
	                ],
	                [
	                  -103.393554,
	                  20.679495
	                ],
	                [
	                  -103.393573,
	                  20.679492
	                ],
	                [
	                  -103.393591,
	                  20.679488
	                ],
	                [
	                  -103.393609,
	                  20.679483
	                ],
	                [
	                  -103.393627,
	                  20.679478
	                ],
	                [
	                  -103.393645,
	                  20.679471
	                ],
	                [
	                  -103.393662,
	                  20.679463
	                ],
	                [
	                  -103.393679,
	                  20.679455
	                ],
	                [
	                  -103.393695,
	                  20.679446
	                ],
	                [
	                  -103.393711,
	                  20.679436
	                ],
	                [
	                  -103.393726,
	                  20.679425
	                ],
	                [
	                  -103.393741,
	                  20.679414
	                ],
	                [
	                  -103.393755,
	                  20.679401
	                ],
	                [
	                  -103.393768,
	                  20.679388
	                ],
	                [
	                  -103.393781,
	                  20.679375
	                ],
	                [
	                  -103.393792,
	                  20.679361
	                ],
	                [
	                  -103.393803,
	                  20.679346
	                ],
	                [
	                  -103.393813,
	                  20.679331
	                ],
	                [
	                  -103.393823,
	                  20.679315
	                ],
	                [
	                  -103.393831,
	                  20.679299
	                ],
	                [
	                  -103.393838,
	                  20.679283
	                ],
	                [
	                  -103.393845,
	                  20.679266
	                ],
	                [
	                  -103.393851,
	                  20.679249
	                ],
	                [
	                  -103.393855,
	                  20.679232
	                ],
	                [
	                  -103.393859,
	                  20.679214
	                ],
	                [
	                  -103.393862,
	                  20.679196
	                ],
	                [
	                  -103.393863,
	                  20.679178
	                ],
	                [
	                  -103.393864,
	                  20.679161
	                ],
	                [
	                  -103.393864,
	                  20.679143
	                ],
	                [
	                  -103.393862,
	                  20.679125
	                ],
	                [
	                  -103.39386,
	                  20.679107
	                ],
	                [
	                  -103.393857,
	                  20.679089
	                ],
	                [
	                  -103.393836,
	                  20.679027
	                ],
	                [
	                  -103.394698,
	                  20.678836
	                ],
	                [
	                  -103.394734,
	                  20.678831
	                ],
	                [
	                  -103.395517,
	                  20.678708
	                ],
	                [
	                  -103.395649,
	                  20.678699
	                ],
	                [
	                  -103.396106,
	                  20.678665
	                ],
	                [
	                  -103.396757,
	                  20.678618
	                ],
	                [
	                  -103.397287,
	                  20.678581
	                ],
	                [
	                  -103.397275,
	                  20.678958
	                ],
	                [
	                  -103.397231,
	                  20.679055
	                ],
	                [
	                  -103.397152,
	                  20.679224
	                ],
	                [
	                  -103.396992,
	                  20.679448
	                ],
	                [
	                  -103.396793,
	                  20.679723
	                ],
	                [
	                  -103.396662,
	                  20.679965
	                ],
	                [
	                  -103.396607,
	                  20.680228
	                ],
	                [
	                  -103.397222,
	                  20.680221
	                ],
	                [
	                  -103.397576,
	                  20.680219
	                ],
	                [
	                  -103.398628,
	                  20.680214
	                ],
	                [
	                  -103.398996,
	                  20.680245
	                ],
	                [
	                  -103.399281,
	                  20.680326
	                ],
	                [
	                  -103.399132,
	                  20.68087
	                ],
	                [
	                  -103.39911,
	                  20.68095
	                ],
	                [
	                  -103.399041,
	                  20.681197
	                ],
	                [
	                  -103.398984,
	                  20.681398
	                ],
	                [
	                  -103.398951,
	                  20.681517
	                ],
	                [
	                  -103.398896,
	                  20.681894
	                ],
	                [
	                  -103.398887,
	                  20.682016
	                ],
	                [
	                  -103.398879,
	                  20.682116
	                ],
	                [
	                  -103.39891,
	                  20.682685
	                ],
	                [
	                  -103.39895,
	                  20.68298
	                ],
	                [
	                  -103.39897,
	                  20.683106
	                ],
	                [
	                  -103.399005,
	                  20.683323
	                ],
	                [
	                  -103.399054,
	                  20.683525
	                ],
	                [
	                  -103.399137,
	                  20.683865
	                ],
	                [
	                  -103.399229,
	                  20.684262
	                ],
	                [
	                  -103.399571,
	                  20.685319
	                ],
	                [
	                  -103.3997,
	                  20.685524
	                ],
	                [
	                  -103.399847,
	                  20.685569
	                ],
	                [
	                  -103.400311,
	                  20.685537
	                ],
	                [
	                  -103.401153,
	                  20.68551
	                ],
	                [
	                  -103.401026,
	                  20.683906
	                ],
	                [
	                  -103.400936,
	                  20.68307
	                ],
	                [
	                  -103.400833,
	                  20.682177
	                ],
	                [
	                  -103.400822,
	                  20.681676
	                ],
	                [
	                  -103.401047,
	                  20.681646
	                ],
	                [
	                  -103.401485,
	                  20.681596
	                ],
	                [
	                  -103.401577,
	                  20.681541
	                ],
	                [
	                  -103.401678,
	                  20.681467
	                ],
	                [
	                  -103.401748,
	                  20.681406
	                ],
	                [
	                  -103.401803,
	                  20.681336
	                ],
	                [
	                  -103.401916,
	                  20.681322
	                ],
	                [
	                  -103.402392,
	                  20.681288
	                ],
	                [
	                  -103.403077,
	                  20.681202
	                ],
	                [
	                  -103.403086,
	                  20.681581
	                ],
	                [
	                  -103.403624,
	                  20.681545
	                ],
	                [
	                  -103.403618,
	                  20.680884
	                ],
	                [
	                  -103.403613,
	                  20.680031
	                ],
	                [
	                  -103.403612,
	                  20.679852
	                ],
	                [
	                  -103.403632,
	                  20.679068
	                ],
	                [
	                  -103.403639,
	                  20.678772
	                ],
	                [
	                  -103.403614,
	                  20.677945
	                ],
	                [
	                  -103.402445,
	                  20.6781
	                ],
	                [
	                  -103.402555,
	                  20.675558
	                ],
	                [
	                  -103.401701,
	                  20.675233
	                ],
	                [
	                  -103.400661,
	                  20.674832
	                ],
	                [
	                  -103.40007,
	                  20.67461
	                ],
	                [
	                  -103.399654,
	                  20.674456
	                ],
	                [
	                  -103.399175,
	                  20.674467
	                ],
	                [
	                  -103.397827,
	                  20.674434
	                ],
	                [
	                  -103.397403,
	                  20.674423
	                ],
	                [
	                  -103.396093,
	                  20.674426
	                ],
	                [
	                  -103.394756,
	                  20.674427
	                ],
	                [
	                  -103.394007,
	                  20.674429
	                ],
	                [
	                  -103.393596,
	                  20.674429
	                ],
	                [
	                  -103.393501,
	                  20.674429
	                ],
	                [
	                  -103.393375,
	                  20.674428
	                ],
	                [
	                  -103.392462,
	                  20.674421
	                ],
	                [
	                  -103.391646,
	                  20.674419
	                ],
	                [
	                  -103.391473,
	                  20.674421
	                ],
	                [
	                  -103.390988,
	                  20.674423
	                ],
	                [
	                  -103.390474,
	                  20.674425
	                ],
	                [
	                  -103.39024,
	                  20.674425
	                ],
	                [
	                  -103.389505,
	                  20.674426
	                ],
	                [
	                  -103.388778,
	                  20.674426
	                ],
	                [
	                  -103.387956,
	                  20.674428
	                ],
	                [
	                  -103.387801,
	                  20.674428
	                ],
	                [
	                  -103.387671,
	                  20.674715
	                ],
	                [
	                  -103.387116,
	                  20.674801
	                ],
	                [
	                  -103.38706,
	                  20.674884
	                ],
	                [
	                  -103.386662,
	                  20.675483
	                ],
	                [
	                  -103.386637,
	                  20.675521
	                ],
	                [
	                  -103.386554,
	                  20.675646
	                ],
	                [
	                  -103.385878,
	                  20.676662
	                ],
	                [
	                  -103.385867,
	                  20.676678
	                ],
	                [
	                  -103.38574,
	                  20.676868
	                ],
	                [
	                  -103.385242,
	                  20.677612
	                ],
	                [
	                  -103.385224,
	                  20.677639
	                ],
	                [
	                  -103.385096,
	                  20.67783
	                ],
	                [
	                  -103.384746,
	                  20.67835
	                ],
	                [
	                  -103.384627,
	                  20.678527
	                ],
	                [
	                  -103.384219,
	                  20.679149
	                ],
	                [
	                  -103.384207,
	                  20.679166
	                ],
	                [
	                  -103.384189,
	                  20.679157
	                ],
	                [
	                  -103.384169,
	                  20.67915
	                ],
	                [
	                  -103.38415,
	                  20.679143
	                ],
	                [
	                  -103.38413,
	                  20.679137
	                ],
	                [
	                  -103.38411,
	                  20.679132
	                ],
	                [
	                  -103.384089,
	                  20.679129
	                ],
	                [
	                  -103.384069,
	                  20.679126
	                ],
	                [
	                  -103.384048,
	                  20.679124
	                ],
	                [
	                  -103.384027,
	                  20.679123
	                ],
	                [
	                  -103.384006,
	                  20.679124
	                ],
	                [
	                  -103.383985,
	                  20.679125
	                ],
	                [
	                  -103.383965,
	                  20.679128
	                ],
	                [
	                  -103.383944,
	                  20.679131
	                ],
	                [
	                  -103.383924,
	                  20.679135
	                ],
	                [
	                  -103.383904,
	                  20.679141
	                ],
	                [
	                  -103.383884,
	                  20.679147
	                ],
	                [
	                  -103.383865,
	                  20.679154
	                ],
	                [
	                  -103.383846,
	                  20.679163
	                ],
	                [
	                  -103.383827,
	                  20.679172
	                ],
	                [
	                  -103.38381,
	                  20.679182
	                ],
	                [
	                  -103.383792,
	                  20.679193
	                ],
	                [
	                  -103.383776,
	                  20.679205
	                ],
	                [
	                  -103.38376,
	                  20.679217
	                ],
	                [
	                  -103.383744,
	                  20.679231
	                ],
	                [
	                  -103.38373,
	                  20.679245
	                ],
	                [
	                  -103.383716,
	                  20.679259
	                ],
	                [
	                  -103.383703,
	                  20.679275
	                ],
	                [
	                  -103.383691,
	                  20.679291
	                ],
	                [
	                  -103.38368,
	                  20.679308
	                ],
	                [
	                  -103.38367,
	                  20.679325
	                ],
	                [
	                  -103.383661,
	                  20.679342
	                ],
	                [
	                  -103.383653,
	                  20.67936
	                ],
	                [
	                  -103.383646,
	                  20.679379
	                ],
	                [
	                  -103.383639,
	                  20.679398
	                ],
	                [
	                  -103.383634,
	                  20.679417
	                ],
	                [
	                  -103.38363,
	                  20.679436
	                ],
	                [
	                  -103.383627,
	                  20.679463
	                ]					
				]
			]
		}
	}]
}
